main.py
base/__init__.py
base/app_dpi_helper.py
base/drag_window.py
base/mouse_through_window.py
base/pin_window.py
base/ring_color_selector_dialog.py
base/shadow_window.py
base/text_modify_dialog.py
canvas_editor/__init__.py
canvas_editor/canvas_commands.py
canvas_editor/canvas_editor.py
canvas_editor/canvas_scene.py
canvas_editor/canvas_view.py
canvas_item/__init__.py
canvas_item/after_effect_util.py
canvas_item/canvas_arrow_item.py
canvas_item/canvas_bubble_text_item.py
canvas_item/canvas_editable_rect.py
canvas_item/canvas_effect_item.py
canvas_item/canvas_eraser_item.py
canvas_item/canvas_line_strip_item.py
canvas_item/canvas_marker_pen.py
canvas_item/canvas_mask_item.py
canvas_item/canvas_number_marker_item.py
canvas_item/canvas_ocr_text_item.py
canvas_item/canvas_paste_image_item.py
canvas_item/canvas_pen_item.py
canvas_item/canvas_quick_qml_item.py
canvas_item/canvas_shape_item.py
canvas_item/canvas_star_item.py
canvas_item/canvas_svg_item.py
canvas_item/canvas_text_item.py
canvas_item/canvas_util.py
common/__init__.py
common/anchor_layout_util.py
common/config.py
common/find_rect_manager.py
common/fuzzy_match.py
common/hotkey.py
common/icon.py
common/logger.py
common/style_sheet.py
common/template_config.py
common/trie.py
common/resource/__init__.py
common/resource/resource_rc.py
extend_widgets/__init__.py
extend_widgets/bubble_tip.py
extend_widgets/color_picker_button_plus.py
extend_widgets/combo_box_setting_card_plus.py
extend_widgets/font_picker_button_plus.py
extend_widgets/key_sequence_edit_plus.py
extend_widgets/setting_card_group_lite.py
manager/__init__.py
manager/pin_window_manager.py
misc/__init__.py
misc/os_helper.py
ocr_loader/__init__.py
ocr_loader/html_builder.py
ocr_loader/ocr_loader_interface.py
ocr_loader/ocr_loader_manager.py
pdf_viewer/__init__.py
pdf_viewer/ocr_widget_interface.py
pdf_viewer/pdf_widget.py
pdf_viewer/web_widget.py
pdf_viewer/__pycache__/__init__.cpython-39.pyc
pdf_viewer/__pycache__/ocr_widget_interface.cpython-39.pyc
ScreenPinKit-3.0.dist-info/METADATA
ScreenPinKit-3.0.dist-info/WHEEL
ScreenPinKit-3.0.dist-info/entry_points.txt
ScreenPinKit-3.0.dist-info/top_level.txt
ScreenPinKit-3.0.dist-info/RECORD
