Metadata-Version: 2.2
Name: ScreenPinKit
Version: 3.0
Summary: A mini screenshot and annotation tool that incorporates ideas from Snipaste, Excalidraw, ShareX, and others.
Home-page: https://github.com/YaoXuanZhi/ScreenPinKit
Author: YaoXuanZhi
Author-email: yaoxuanzhi@outlook.com
License: MIT
Project-URL: Youtube, https://www.youtube.com/playlist?list=PL3uuKTASzjRYNdl7wYlgUd7agQIA2_y5V
Project-URL: Documentation, https://github.com/YaoXuanZhi/ScreenPinKit/wiki
Project-URL: Source Code, https://github.com/YaoXuanZhi/ScreenPinKit
Project-URL: Bug Tracker, https://github.com/YaoXuanZhi/ScreenPinKit/issues
Keywords: pyqt ScreenPinKit screenshot screen-paint
Classifier: Programming Language :: Python :: 3.8
Classifier: Programming Language :: Python :: 3.9
Classifier: License :: OSI Approved :: MIT License
Classifier: Operating System :: OS Independent
Requires-Dist: PyQt5>=5.15.0
Requires-Dist: scipy
Requires-Dist: pillow<=9.5.0
Requires-Dist: PyQt-Fluent-Widgets
Requires-Dist: PyQtWebEngine
Requires-Dist: system_hotkey
Requires-Dist: opencv-python==4.10.0.84
Requires-Dist: opencv-contrib-python==4.10.0.84
Requires-Dist: onnxruntime==1.19.2
Requires-Dist: pyclipper
Requires-Dist: shapely==2.0.6
Requires-Dist: fuzzywuzzy
Requires-Dist: python-Levenshtein
Requires-Dist: sortedcontainers
Requires-Dist: requests
Dynamic: author
Dynamic: author-email
Dynamic: classifier
Dynamic: description
Dynamic: description-content-type
Dynamic: home-page
Dynamic: keywords
Dynamic: license
Dynamic: project-url
Dynamic: requires-dist
Dynamic: summary
